{"data":{"_id":1000,"properties":{"id":{"name":"id","kind":"scalar","primary":true,"type":"uuid","array":false,"runtimeType":"string"},"pricePaidInCents":{"name":"pricePaidInCents","kind":"scalar","type":"int","nullable":false,"getter":false,"setter":false,"array":false,"runtimeType":"number"},"productDetails":{"name":"productDetails","kind":"scalar","nullable":false,"getter":false,"setter":false,"columnTypes":["json"],"type":"{ name: string; description: string; image_url: string; }","array":false,"runtimeType":"{ name: string; description: string; image_url: string; }"},"stripeSessionId":{"name":"stripeSessionId","kind":"scalar","type":"string","unique":true,"getter":false,"setter":false,"array":false,"runtimeType":"string"},"stripePaymentIntentId":{"name":"stripePaymentIntentId","kind":"scalar","type":"string","nullable":true,"unique":true,"getter":false,"setter":false,"array":false,"runtimeType":"string"},"status":{"name":"status","kind":"scalar","enum":true,"items":["pending","paid","refunded"],"default":"pending","type":"PurchaseStatus","array":false,"runtimeType":"PurchaseStatus"},"refundedAt":{"name":"refundedAt","kind":"scalar","type":"timestamp","nullable":true,"getter":false,"setter":false,"array":false,"runtimeType":"Date"},"createdAt":{"name":"createdAt","kind":"scalar","type":"timestamp","defaultRaw":"CURRENT_TIMESTAMP","getter":false,"setter":false,"array":false,"runtimeType":"Date"},"updatedAt":{"name":"updatedAt","kind":"scalar","type":"timestamp","defaultRaw":"CURRENT_TIMESTAMP","getter":false,"setter":false,"array":false,"runtimeType":"Date"},"user":{"name":"user","kind":"m:1","cascade":["persist"],"deleteRule":"set null","owner":true,"fieldNames":["user_id"],"type":"User","array":false,"runtimeType":"User"},"product":{"name":"product","kind":"m:1","cascade":["persist"],"deleteRule":"set null","owner":true,"fieldNames":["product_id"],"type":"Product","array":false,"runtimeType":"Product"}},"primaryKeys":["id"],"filters":{},"hooks":{},"indexes":[],"uniques":[],"className":"Purchase","path":"./src/purchases/entities/purchase.entity.ts","collection":"purchases","name":"Purchase","abstract":false,"internal":true,"constructorParams":[],"toJsonParams":[],"useCache":true,"compositePK":false,"simplePK":true},"origin":"./src/purchases/entities/purchase.entity.ts","hash":"6ec2b34160f798429865c35b592605c4","version":"6.4.6"}
